missing_text/__init__.py
missing_text/cli.py
missing_text/hello_missing.py
missing_text-0.0.1a5.dist-info/LICENSE
missing_text-0.0.1a5.dist-info/LICENSE.md
missing_text-0.0.1a5.dist-info/METADATA
missing_text-0.0.1a5.dist-info/WHEEL
missing_text-0.0.1a5.dist-info/entry_points.txt
missing_text-0.0.1a5.dist-info/top_level.txt
missing_text-0.0.1a5.dist-info/RECORD
