Metadata-Version: 2.1
Name: missing-text
Version: 0.0.1a5
Summary: A package purpose built for simplifying document processing for LLM based application development
Author-email: Maruthi <maruthi@typeless.io>, Bryan <bryan.leezc@gmail.com>
Project-URL: Homepage, https://github.com/typeless-io/missing_text
Classifier: Programming Language :: Python :: 3
Classifier: Programming Language :: Python :: 3.10
Classifier: Programming Language :: Python :: 3.11
Classifier: Programming Language :: Python :: 3.12
Classifier: License :: OSI Approved :: Apache Software License
Classifier: Operating System :: OS Independent
Requires-Python: >=3.10
License-File: LICENSE
License-File: LICENSE.md
Requires-Dist: fastapi>=0.115.0
Requires-Dist: pydantic>=2.9.2
Requires-Dist: pymupdf>=1.24.11
Requires-Dist: pytesseract>=0.3.13
Requires-Dist: python-multipart>=0.0.12
Requires-Dist: uvicorn>=0.31.0
Requires-Dist: click>=8.1.7
Requires-Dist: python-dotenv>=1.0.1
